landregistry/trace_id/__init__.py
landregistry/trace_id/extension.py
landregistry/trace_id/py.typed
landregistry_trace_id-2.0.1.dist-info/METADATA
landregistry_trace_id-2.0.1.dist-info/WHEEL
landregistry_trace_id-2.0.1.dist-info/top_level.txt
landregistry_trace_id-2.0.1.dist-info/RECORD
