Metadata-Version: 2.1
Name: landregistry-trace-id
Version: 2.0.1
Summary: Tracability for HMLR applications
Author: Ian Harvey
Author-email: ian.harvey@landregistry.gov.uk
License: MIT
Requires-Python: >=3.9
Requires-Dist: flask >=2.2.2
